dsjobs/__init__.py
dsjobs/dir.py
dsjobs/jobs.py
dsjobs-0.1.5.dist-info/LICENSE.md
dsjobs-0.1.5.dist-info/METADATA
dsjobs-0.1.5.dist-info/WHEEL
dsjobs-0.1.5.dist-info/RECORD
