Metadata-Version: 2.1
Name: dsjobs
Version: 0.1.5
Summary: DSJobs simplifies accessing TAPIS on DesignSafe
Author: Krishna Kumar
Author-email: krishnak@utexas.edu
Requires-Python: >=3.8,<4.0
Classifier: Programming Language :: Python :: 3
Classifier: Programming Language :: Python :: 3.8
Classifier: Programming Language :: Python :: 3.9
Classifier: Programming Language :: Python :: 3.10
Classifier: Programming Language :: Python :: 3.11
Classifier: Programming Language :: Python :: 3.12
Requires-Dist: agavepy (>0.9.5)
Requires-Dist: exceptiongroup (>=1.1.3,<2.0.0)
Requires-Dist: tqdm (>=4.66.1,<5.0.0)
